pbash/__init__.py
pbash/app.py
pbash/appConfig.py
pbash/modules/commands.py
pbash/modules/git.py
pbash/modules/params.py
pbash/modules/ui.py
pbash-0.1.0.dist-info/entry_points.txt
pbash-0.1.0.dist-info/WHEEL
pbash-0.1.0.dist-info/METADATA
pbash-0.1.0.dist-info/RECORD
