Metadata-Version: 2.1
Name: pbash
Version: 0.1.0
Summary: Bash Script Manager
Home-page: https://github.com/sguerri/pbash
License: GPL-3.0
Author: Sebastien GUERRI
Author-email: nierrgu@bmel.fr
Requires-Python: >=3.6.2,<4.0
Classifier: License :: OSI Approved :: GNU General Public License v3 (GPLv3)
Classifier: Programming Language :: Python :: 3
Classifier: Programming Language :: Python :: 3.10
Classifier: Programming Language :: Python :: 3.7
Classifier: Programming Language :: Python :: 3.8
Classifier: Programming Language :: Python :: 3.9
Requires-Dist: click (>=8.0.4,<9.0.0)
Requires-Dist: rich (>=11.2.0,<12.0.0)
Project-URL: Repository, https://github.com/sguerri/pbash
